MANIFEST.in
VERSION
setup.py
libcanonical/__init__.py
libcanonical/cli.py
libcanonical/code.py
libcanonical/const.py
libcanonical/environ.py
libcanonical/package.json
libcanonical.egg-info/PKG-INFO
libcanonical.egg-info/SOURCES.txt
libcanonical.egg-info/dependency_links.txt
libcanonical.egg-info/requires.txt
libcanonical.egg-info/top_level.txt
libcanonical/bases/__init__.py
libcanonical/bases/_environmentbasemodel.py
libcanonical/bases/_externalstate.py
libcanonical/bases/_lifecycled.py
libcanonical/bases/_pollingexternalstate.py
libcanonical/bases/_regexclassifier.py
libcanonical/bases/_statelogger.py
libcanonical/bases/_taggable.py
libcanonical/protocols/__init__.py
libcanonical/protocols/_isigner.py
libcanonical/protocols/_itransaction.py
libcanonical/runtime/__init__.py
libcanonical/runtime/_logging.py
libcanonical/runtime/_mainprocess.py
libcanonical/runtime/_signalhandler.py
libcanonical/types/__init__.py
libcanonical/types/applicationruntimestate.py
libcanonical/types/awaitablebool.py
libcanonical/types/awaitablebytes.py
libcanonical/types/base64.py
libcanonical/types/base64int.py
libcanonical/types/base64json.py
libcanonical/types/base64type.py
libcanonical/types/base64urlencoded.py
libcanonical/types/bcp47.py
libcanonical/types/bytestype.py
libcanonical/types/colonseparatedlist.py
libcanonical/types/colonseparatedset.py
libcanonical/types/digestsha256.py
libcanonical/types/domainname.py
libcanonical/types/emailaddress.py
libcanonical/types/hexencoded.py
libcanonical/types/httpheadertype.py
libcanonical/types/httprequestref.py
libcanonical/types/httpresourcelocator.py
libcanonical/types/httpretryafter.py
libcanonical/types/jsonpath.py
libcanonical/types/phonenumber.py
libcanonical/types/pythonsymbol.py
libcanonical/types/resourcename.py
libcanonical/types/serializableset.py
libcanonical/types/stringorset.py
libcanonical/types/stringrepresentable.py
libcanonical/types/stringtype.py
libcanonical/types/unixtimestamp.py
libcanonical/types/websocketresourcelocator.py
libcanonical/types/crypto/__init__.py
libcanonical/types/crypto/_aesencryptionresult.py
libcanonical/types/crypto/_baseencryptionresult.py
